[
  {
    "id": "id_1780235868274_lgk30p",
    "name": "Gibson",
    "phone": "62117230",
    "datetime": "2026-06-01T10:00",
    "count": 2,
    "note": "青洲大馬路 青怡大廈 二座 10 A",
    "price": 218
  },
  {
    "id": "id_1780236021994_n73iaq",
    "name": "Jeni",
    "phone": "66856996",
    "datetime": "2026-06-01T11:30",
    "count": 1,
    "note": "粵德大廈",
    "price": 218
  },
  {
    "id": "id_1780236069202_q028de",
    "name": "Calvin",
    "phone": "66600994",
    "datetime": "2026-06-01T02:00",
    "count": 3,
    "note": "氹仔華寶花園第三座8M",
    "price": 238
  },
  {
    "id": "id_1780236223322_w0el3p",
    "name": "Iceice",
    "phone": "66601474",
    "datetime": "2026-06-02T10:00",
    "count": 3,
    "note": "路環蝴蝶谷大馬路居雅第五座 14樓AT",
    "price": 228
  },
  {
    "id": "id_1780236269714_01phrn",
    "name": "Kawai",
    "phone": "63835678",
    "datetime": "2026-06-02T01:00",
    "count": 3,
    "note": "澳門國際中心七座9C",
    "price": 218
  },
  {
    "id": "id_1780236547564_0n09lz",
    "name": "Feifei",
    "phone": "66801471",
    "datetime": "2026-06-03T10:00",
    "count": 3,
    "note": "青怡大廈第一座 15樓D",
    "price": 218
  },
  {
    "id": "id_1780236595156_ywuiwe",
    "name": "Lino",
    "phone": "63001201",
    "datetime": "2026-06-03T02:30",
    "count": 2,
    "note": "台山逸麗花園第四座11樓Z",
    "price": 238
  },
  {
    "id": "id_1780236644956_h3yg9k",
    "name": "I.m cherry",
    "phone": "63876132",
    "datetime": "2026-06-04T10:00",
    "count": 3,
    "note": "青州坊3座7樓M",
    "price": 228
  },
  {
    "id": "id_1780236727301_u8yy8d",
    "name": "Ray",
    "phone": "66129484",
    "datetime": "2026-06-06T10:00",
    "count": 2,
    "note": "氹仔南京街417號濠庭都會14座15樓D",
    "price": 238
  },
  {
    "id": "id_1780236793108_14kd4y",
    "name": "Cindy yum",
    "phone": "66130387",
    "datetime": "2026-06-06T12:30",
    "count": 2,
    "note": "海天居第五座30/C",
    "price": 228
  },
  {
    "id": "id_1780236830666_vsp7hl",
    "name": "打不過就加入",
    "phone": "63943036",
    "datetime": "2026-06-06T02:30",
    "count": 3,
    "note": "提督馬路郎悅居5樓B 新苗樓上",
    "price": 218,
    "status": "completed"
  },
  {
    "id": "id_1780236884484_5hr2mb",
    "name": "雷生",
    "phone": "63713939",
    "datetime": "2026-06-06T04:00",
    "count": 3,
    "note": "下環街鹹魚街1 號環安大廈3 樓b座",
    "price": 238
  },
  {
    "id": "id_1780304649977_90ufgn",
    "name": "阿黃",
    "phone": "66815301",
    "datetime": "2026-06-09T02:30",
    "count": 3,
    "note": "白鴿巢前地",
    "price": 218
  },
  {
    "id": "id_1780304764661_h07kz8",
    "name": "Zoey",
    "phone": "62525707",
    "datetime": "2026-06-09T10:30",
    "count": 3,
    "note": "林茂塘海邊街24號",
    "price": 218
  },
  {
    "id": "id_1780304837901_1ngaby",
    "name": "晶晶",
    "phone": "62350811",
    "datetime": "2026-06-13T02:30",
    "count": 2,
    "note": "嘉應花園第一座18楼G",
    "price": 218
  },
  {
    "id": "id_1780304883361_zw9jgf",
    "name": "Anthony",
    "phone": "66611153",
    "datetime": "2026-06-13T04:00",
    "count": 4,
    "note": "海上居第一座20 樓D",
    "price": 228
  },
  {
    "id": "id_1780305160301_d5ebyx",
    "name": "Fai",
    "phone": "66605248",
    "datetime": "2026-06-11T01:00",
    "count": 6,
    "note": "氹仔萬國華庭第一座11樓 B",
    "price": 228
  },
  {
    "id": "id_1780388678925_rpg718",
    "name": "KT",
    "phone": "66870855",
    "datetime": "2026-07-04T10:00",
    "count": 3,
    "note": "文第士街 漢益大廈 5樓b",
    "price": 228
  },
  {
    "id": "id_1780389512117_82c5j5",
    "name": "Catherine",
    "phone": "66675759",
    "datetime": "2026-06-04T01:00",
    "count": 2,
    "note": "居大馬路居雅大廈水第一座水仙苑6樓J座",
    "price": 228
  },
  {
    "id": "id_1780393892849_jx8z4c",
    "name": "Danleong",
    "phone": "66637491",
    "datetime": "2026-06-04T02:30",
    "count": 2,
    "note": "",
    "price": 228
  },
  {
    "id": "id_1780407366494_69ra5i",
    "name": "Betty",
    "phone": "66367713",
    "datetime": "2026-06-07T10:30",
    "count": 4,
    "note": "信譽名門一座19樓F單元",
    "price": 228,
    "status": "completed"
  },
  {
    "id": "id_1780409236436_p4i64o",
    "name": "Nana",
    "phone": "62311150",
    "datetime": "2026-06-07T01:30",
    "count": 4,
    "note": "澳門  爹美刁施拿地大馬路3號典雅灣6樓C",
    "price": 218,
    "status": "completed"
  },
  {
    "id": "id_1780484237417_8hfpv4",
    "name": "Bunnie",
    "phone": "63683898",
    "datetime": "2026-06-05T09:30",
    "count": 2,
    "note": "新口岸南岸花園第四座10s",
    "price": 218,
    "status": "completed"
  },
  {
    "id": "id_1780543924528_m02t8b",
    "name": "嘉儀",
    "phone": "66833013",
    "datetime": "2026-06-18T09:30",
    "count": 5,
    "note": "澳門羅利老馬路蘆苑16D",
    "price": 238,
    "status": "pending"
  },
  {
    "id": "id_1780560572055_85wvh4",
    "name": "Kimi",
    "phone": "68651036",
    "datetime": "2026-06-08T10:00",
    "count": 2,
    "note": "澳門洞穴街46號金馬花園第二期2樓I",
    "price": 238,
    "status": "pending"
  },
  {
    "id": "id_1780563685061_0cg07r",
    "name": "澳門岳",
    "phone": "63122002",
    "datetime": "2026-06-18T01:30",
    "count": 4,
    "note": "海上居第三座 6樓 G",
    "price": 218,
    "status": "pending"
  },
  {
    "id": "id_1780584811161_q0e09h",
    "name": "Jimmy",
    "phone": "65588846",
    "datetime": "2026-06-10T09:30",
    "count": 3,
    "note": "鏡湖馬路79號輝恆大廈四樓C座",
    "price": 238,
    "status": "pending"
  },
  {
    "id": "id_1780629581271_rdlvxn",
    "name": "Ling",
    "phone": "66635228",
    "datetime": "2026-06-23T09:30",
    "count": 4,
    "note": "黑沙環利添閣5樓x",
    "price": 218,
    "status": "pending"
  },
  {
    "id": "id_1780631246541_f97oi8",
    "name": "Sun",
    "phone": "63394933",
    "datetime": "2026-06-12T12:30",
    "count": 3,
    "note": "長崎街金豐大廈第一座4E",
    "price": 218,
    "status": "pending"
  },
  {
    "id": "id_1780654566555_y4n9km",
    "name": "Ringo",
    "phone": "66639919",
    "datetime": "2026-06-19T01:00",
    "count": 3,
    "note": "皇朝帝景苑4座14J",
    "price": 238,
    "status": "pending"
  },
  {
    "id": "id_1780671574923_03a1ws",
    "name": "Jenny",
    "phone": "66671833",
    "datetime": "2026-06-24T03:30",
    "count": 4,
    "note": "氹仔美景花園第二座美寶閣14G",
    "price": 228,
    "status": "pending"
  },
  {
    "id": "id_1780746352320_wyvcgt",
    "name": "Patricklao",
    "phone": "66120494",
    "datetime": "2026-06-17T10:00",
    "count": 5,
    "note": "澳門竹室正街一號富華樓1樓 B",
    "price": 218,
    "status": "pending"
  },
  {
    "id": "id_1780806355670_e9f19w",
    "name": "Irs",
    "phone": "62788123",
    "datetime": "2026-06-13T11:30",
    "count": 2,
    "note": "筷子基綠楊花園第二座利泰閣23/X",
    "price": 218,
    "status": "pending"
  },
  {
    "id": "id_1780808703104_mamcgd",
    "name": "陳燦",
    "phone": "66697277",
    "datetime": "2026-06-19T09:30",
    "count": 3,
    "note": "筷子基俾若翰街快盈大廈一座7樓i室",
    "price": 238,
    "status": "pending"
  },
  {
    "id": "id_1780822210262_09n8ll",
    "name": "Paggy",
    "phone": "65369080",
    "datetime": "2026-06-12T09:30",
    "count": 2,
    "note": "黑沙環永寧威龍花園第一座6S",
    "price": 238,
    "status": "pending"
  },
  {
    "id": "id_1780894705403_5zd1xo",
    "name": "Nana",
    "phone": "66108795",
    "datetime": "2026-06-14T01:30",
    "count": 3,
    "note": "氹仔鴻發花園第二座",
    "price": 228,
    "status": "pending"
  },
  {
    "id": "id_1780894825645_pxuhn0",
    "name": "玲玲",
    "phone": "66889523",
    "datetime": "2026-06-11T11:00",
    "count": 2,
    "note": "氹仔 東北馬路 聚龍明珠 第一座10 A",
    "price": 248,
    "status": "pending"
  }
]